pmaker/__init__.py
pmaker/enter.py
pmaker/invokation.py
pmaker/invokation_manager.py
pmaker/jobhelper.py
pmaker/judge.py
pmaker/ui/__init__.py
pmaker/ui/web/404.html
pmaker/ui/web/__init__.py
pmaker/ui/web/invokation.html
pmaker/ui/web/invokation_compilation.html
pmaker/ui/web/invokation_list.html
pmaker/ui/web/invokation_run.html
pmaker/ui/web/style.css
pmaker/ui/web/test_verbose.html
pmaker/ui/web/test_view.html
pmaker/ui/web/testview.html
pmaker/ui/web/web.py
pmaker-0.3.0.dist-info/DESCRIPTION.rst
pmaker-0.3.0.dist-info/METADATA
pmaker-0.3.0.dist-info/RECORD
pmaker-0.3.0.dist-info/WHEEL
pmaker-0.3.0.dist-info/entry_points.txt
pmaker-0.3.0.dist-info/metadata.json
pmaker-0.3.0.dist-info/top_level.txt
