Metadata-Version: 2.0
Name: pmaker
Version: 0.3.0
Summary: Toolkit for creating problems for programming competitions
Home-page: https://github.com/p-maker/pmaker
Author: Dmitry Sayutin
Author-email: UNKNOWN
License: UNKNOWN
Platform: UNKNOWN
Requires-Python: >=3.5, <4
